Metadata-Version: 2.1
Name: almost-make
Version: 0.5.2
Summary: A pure-Python implementation of make.
Home-page: https://github.com/personalizedrefrigerator/AlmostMake
Author: Henry Heino
Author-email: personalizedrefrigerator@gmail.com
License: UNKNOWN
Keywords: make,almake,bsdmake,gnumake,Makefile,cli
Platform: UNKNOWN
Classifier: Programming Language :: Python :: 3
Classifier: License :: OSI Approved :: BSD License
Classifier: Development Status :: 3 - Alpha
Classifier: Operating System :: OS Independent
Classifier: Intended Audience :: Developers
Classifier: Intended Audience :: System Administrators
Classifier: Environment :: Console
Requires-Python: >=3.6.8
License-File: LICENSE
